infraweave-0.1.2.dist-info/RECORD
infraweave-0.1.2.dist-info/WHEEL
infraweave-0.1.2.dist-info/METADATA
infraweave/__init__.py
infraweave/infraweave.cpython-312-darwin.so
