Metadata-Version: 2.3
Name: infraweave
Version: 0.1.2
Classifier: License :: OSI Approved :: Apache Software License
Classifier: Development Status :: 3 - Alpha
Summary: Interact with InfraWeave using Python
Author-email: InfraWeave Team <opensource@infraweave.com>
License: Apache-2.0
Requires-Python: >=3.10
Project-URL: Homepage, https://preview.infraweave.io
Project-URL: Documentation, https://infraweave-io.github.io/infraweave/infraweave.html
